coralsnake/.gitignore
coralsnake/__init__.py
coralsnake/annot.py
coralsnake/cli.py
coralsnake/conversion.py
coralsnake/debug.py
coralsnake/gbam2tbam.py
coralsnake/genegroup.py
coralsnake/gtf2tx.py
coralsnake/mapping.py
coralsnake/run.py
coralsnake/run.smk
coralsnake/tbam2gbam.py
coralsnake/utils.py
coralsnake/minimap2/.git
coralsnake/minimap2/.gitignore
coralsnake/minimap2/.gitmodules
coralsnake/minimap2/FAQ.md
coralsnake/minimap2/LICENSE.txt
coralsnake/minimap2/MANIFEST.in
coralsnake/minimap2/Makefile
coralsnake/minimap2/Makefile.simde
coralsnake/minimap2/NEWS.md
coralsnake/minimap2/README.md
coralsnake/minimap2/align.c
coralsnake/minimap2/bseq.c
coralsnake/minimap2/bseq.h
coralsnake/minimap2/code_of_conduct.md
coralsnake/minimap2/cookbook.md
coralsnake/minimap2/esterr.c
coralsnake/minimap2/example.c
coralsnake/minimap2/format.c
coralsnake/minimap2/hit.c
coralsnake/minimap2/index.c
coralsnake/minimap2/kalloc.c
coralsnake/minimap2/kalloc.h
coralsnake/minimap2/kdq.h
coralsnake/minimap2/ketopt.h
coralsnake/minimap2/khash.h
coralsnake/minimap2/krmq.h
coralsnake/minimap2/kseq.h
coralsnake/minimap2/ksort.h
coralsnake/minimap2/ksw2.h
coralsnake/minimap2/ksw2_dispatch.c
coralsnake/minimap2/ksw2_extd2_sse.c
coralsnake/minimap2/ksw2_exts2_sse.c
coralsnake/minimap2/ksw2_extz2_sse.c
coralsnake/minimap2/ksw2_ll_sse.c
coralsnake/minimap2/kthread.c
coralsnake/minimap2/kthread.h
coralsnake/minimap2/kvec.h
coralsnake/minimap2/lchain.c
coralsnake/minimap2/main.c
coralsnake/minimap2/map.c
coralsnake/minimap2/minimap.h
coralsnake/minimap2/minimap2.1
coralsnake/minimap2/misc.c
coralsnake/minimap2/mmpriv.h
coralsnake/minimap2/options.c
coralsnake/minimap2/pe.c
coralsnake/minimap2/pyproject.toml
coralsnake/minimap2/sdust.c
coralsnake/minimap2/sdust.h
coralsnake/minimap2/seed.c
coralsnake/minimap2/setup.py
coralsnake/minimap2/sketch.c
coralsnake/minimap2/splitidx.c
coralsnake/minimap2/.github/workflows/ci.yaml
coralsnake/minimap2/misc/README.md
coralsnake/minimap2/misc/mmphase.js
coralsnake-0.0.98.dist-info/METADATA
coralsnake-0.0.98.dist-info/WHEEL
coralsnake-0.0.98.dist-info/entry_points.txt
coralsnake-0.0.98.dist-info/RECORD
